laakhay/quantlab/__init__.py
laakhay/quantlab/_version.py
laakhay/quantlab/__pycache__/__init__.cpython-313.pyc
laakhay_quantlab-0.1.3.dist-info/METADATA
laakhay_quantlab-0.1.3.dist-info/WHEEL
laakhay_quantlab-0.1.3.dist-info/top_level.txt
laakhay_quantlab-0.1.3.dist-info/RECORD
