Metadata-Version: 2.4
Name: laakhay-quantlab
Version: 0.1.3
Summary: Quant tools built with ♥︎ by Laakhay
Author-email: Laakhay Corporation <laakhay.corp@gmail.com>
License: MIT
Project-URL: Homepage, https://laakhay.com
Project-URL: Repository, https://github.com/laakhay/quantlab
Classifier: Programming Language :: Python :: 3
Classifier: License :: OSI Approved :: MIT License
Classifier: Operating System :: OS Independent
Requires-Python: >=3.6
